nexpresso/__init__.py
nexpresso/expressions.py
nexpresso/hierarchical_packer.py
nexpresso/nexpresso.py
nexpresso/py.typed
nexpresso/structuring_utils.py
polars_nexpresso-0.2.0.dist-info/METADATA
polars_nexpresso-0.2.0.dist-info/WHEEL
polars_nexpresso-0.2.0.dist-info/licenses/LICENSE
polars_nexpresso-0.2.0.dist-info/RECORD
