Metadata-Version: 2.4
Name: polars-nexpresso
Version: 0.2.0
Summary: A utility library for generating Polars expressions to work with nested data structures
Project-URL: Homepage, https://github.com/heshamdar/polars-nexpresso
Project-URL: Documentation, https://heshamdar.github.io/polars-nexpresso
Project-URL: Repository, https://github.com/heshamdar/polars-nexpresso
Project-URL: Issues, https://github.com/heshamdar/polars-nexpresso/issues
Author-email: Hesham Dar <heshamdar@gmail.com>
License: MIT
License-File: LICENSE
Keywords: data-processing,dataframe,expression,nested,nexpresso,polars,struct
Classifier: Development Status :: 4 - Beta
Classifier: Intended Audience :: Developers
Classifier: License :: OSI Approved :: MIT License
Classifier: Programming Language :: Python :: 3
Classifier: Programming Language :: Python :: 3.10
Classifier: Programming Language :: Python :: 3.11
Classifier: Programming Language :: Python :: 3.12
Classifier: Programming Language :: Python :: 3.13
Classifier: Topic :: Scientific/Engineering
Classifier: Topic :: Software Development :: Libraries :: Python Modules
Requires-Python: >=3.10
Requires-Dist: packaging>=21.0
Requires-Dist: polars>=1.20.0
